scrapeready.py
scrapeready-1.0.0.dist-info/LICENSE
scrapeready-1.0.0.dist-info/METADATA
scrapeready-1.0.0.dist-info/WHEEL
scrapeready-1.0.0.dist-info/top_level.txt
scrapeready-1.0.0.dist-info/RECORD
