Metadata-Version: 2.2
Name: scrapeready
Version: 1.0.0
Summary: A Python client for the scrapeready.com v1 API
Author-email: Aiden <aiden@foptciy.com>
License: MIT License
Project-URL: Homepage, https://github.com/foptciy/scrapeready-sdk
Project-URL: Source, https://github.com/foptciy/scrapeready-sdk
Project-URL: Tracker, https://github.com/foptciy/scrapeready-sdk/issues
Keywords: scraping,serp,ai,scrapeready
Classifier: Programming Language :: Python :: 3
Classifier: License :: OSI Approved :: MIT License
Classifier: Operating System :: OS Independent
Requires-Python: >=3.7
License-File: LICENSE
Requires-Dist: requests>=2.20.0
